os_acc/__init__.py
os_acc/base.py
os_acc/exception.py
os_acc/i18n.py
os_acc/pci.py
os_acc/version.py
os_acc/tests/__init__.py
os_acc/tests/functional/__init__.py
os_acc/tests/unit/__init__.py
os_acc/tests/unit/base.py
os_acc/tests/unit/test_exception.py
os_acc/tests/unit/test_os_acc.py
os_acc/tests/unit/test_pci.py
os_acc-0.2.0.dist-info/AUTHORS
os_acc-0.2.0.dist-info/LICENSE
os_acc-0.2.0.dist-info/METADATA
os_acc-0.2.0.dist-info/WHEEL
os_acc-0.2.0.dist-info/entry_points.txt
os_acc-0.2.0.dist-info/pbr.json
os_acc-0.2.0.dist-info/top_level.txt
os_acc-0.2.0.dist-info/RECORD
