Metadata-Version: 2.1
Name: os-acc
Version: 0.2.0
Summary: A library for attaching and detaching accelerators in OpenStack.
Home-page: https://docs.openstack.org/
Author: OpenStack
Author-email: openstack-dev@lists.openstack.org
License: UNKNOWN
Platform: UNKNOWN
Classifier: Environment :: OpenStack
Classifier: Intended Audience :: Information Technology
Classifier: Intended Audience :: System Administrators
Classifier: License :: OSI Approved :: Apache Software License
Classifier: Operating System :: POSIX :: Linux
Classifier: Programming Language :: Python
Classifier: Programming Language :: Python :: 2
Classifier: Programming Language :: Python :: 2.7
Classifier: Programming Language :: Python :: 3
Classifier: Programming Language :: Python :: 3.5
Requires-Dist: pbr (!=2.1.0,>=2.0.0)
Requires-Dist: oslo.config (>=5.1.0)
Requires-Dist: oslo.log (>=3.30.0)
Requires-Dist: oslo.i18n (>=3.15.3)
Requires-Dist: six (>=1.10.0)
Requires-Dist: stevedore (>=1.20.0)
